mortalite_tablosu/__init__.py
mortalite_tablosu/mortalite_tablosu.py
mortalite_tablosu/similasyon.py
mortalite_tablosu-0.1.0.dist-info/licenses/LICENSE
mortalite_tablosu-0.1.0.dist-info/METADATA
mortalite_tablosu-0.1.0.dist-info/WHEEL
mortalite_tablosu-0.1.0.dist-info/top_level.txt
mortalite_tablosu-0.1.0.dist-info/RECORD
