Metadata-Version: 2.4
Name: mortalite-tablosu
Version: 0.1.0
Summary: Mortalite tablosu ve simulasyon hesapları
Author: Dilara Eslem
License: MIT
Requires-Python: >=3.8
License-File: LICENSE
Dynamic: license-file
